{
  "firstLayout": "",
  "gdVersion": {
    "build": 98,
    "major": 4,
    "minor": 0,
    "revision": 0
  },
  "properties": {
    "adMobAppId": "",
    "adaptGameResolutionAtRuntime": true,
    "folderProject": false,
    "linuxExecutableFilename": "",
    "macExecutableFilename": "",
    "orientation": "landscape",
    "packageName": "com.example.gamename",
    "projectFile": "/home/miguel/Área de trabalho/ProjetosGDevelop/QuarentineDays/GameCode/game.json",
    "scaleMode": "linear",
    "sizeOnStartupMode": "adaptWidth",
    "useExternalSourceFiles": false,
    "version": "1.0.0",
    "winExecutableFilename": "",
    "winExecutableIconFile": "",
    "name": "QuarentineDays",
    "author": "Miguel De Souza Ribeiro",
    "windowWidth": 640,
    "windowHeight": 320,
    "latestCompilationDirectory": "",
    "maxFPS": 60,
    "minFPS": 20,
    "verticalSync": false,
    "platformSpecificAssets": {},
    "loadingScreen": {
      "showGDevelopSplash": true
    },
    "extensions": [
      {
        "name": "BuiltinObject"
      },
      {
        "name": "BuiltinAudio"
      },
      {
        "name": "BuiltinVariables"
      },
      {
        "name": "BuiltinTime"
      },
      {
        "name": "BuiltinMouse"
      },
      {
        "name": "BuiltinKeyboard"
      },
      {
        "name": "BuiltinJoystick"
      },
      {
        "name": "BuiltinCamera"
      },
      {
        "name": "BuiltinWindow"
      },
      {
        "name": "BuiltinFile"
      },
      {
        "name": "BuiltinNetwork"
      },
      {
        "name": "BuiltinScene"
      },
      {
        "name": "BuiltinAdvanced"
      },
      {
        "name": "Sprite"
      },
      {
        "name": "BuiltinCommonInstructions"
      },
      {
        "name": "BuiltinCommonConversions"
      },
      {
        "name": "BuiltinStringInstructions"
      },
      {
        "name": "BuiltinMathematicalTools"
      },
      {
        "name": "BuiltinExternalLayouts"
      }
    ],
    "platforms": [
      {
        "name": "GDevelop JS platform"
      }
    ],
    "currentPlatform": "GDevelop JS platform"
  },
  "resources": {
    "resources": [
      {
        "alwaysLoaded": false,
        "file": "Assets/Bars/FoodBar/FoodBar1.png",
        "kind": "image",
        "metadata": "",
        "name": "Assets/Bars/FoodBar/FoodBar1.png",
        "smoothed": true,
        "userAdded": true
      },
      {
        "alwaysLoaded": false,
        "file": "Assets/Bars/FoodBar/FoodBar2.png",
        "kind": "image",
        "metadata": "",
        "name": "Assets/Bars/FoodBar/FoodBar2.png",
        "smoothed": true,
        "userAdded": true
      },
      {
        "alwaysLoaded": false,
        "file": "Assets/Bars/FoodBar/FoodBar3.png",
        "kind": "image",
        "metadata": "",
        "name": "Assets/Bars/FoodBar/FoodBar3.png",
        "smoothed": true,
        "userAdded": true
      },
      {
        "alwaysLoaded": false,
        "file": "Assets/Bars/FoodBar/FullFoodBar.png",
        "kind": "image",
        "metadata": "",
        "name": "Assets/Bars/FoodBar/FullFoodBar.png",
        "smoothed": true,
        "userAdded": true
      },
      {
        "alwaysLoaded": false,
        "file": "Assets/Bars/FoodBar/FoodBar4.png",
        "kind": "image",
        "metadata": "",
        "name": "Assets/Bars/FoodBar/FoodBar4.png",
        "smoothed": true,
        "userAdded": true
      },
      {
        "alwaysLoaded": false,
        "file": "FoodBar1.png",
        "kind": "image",
        "metadata": "",
        "name": "FoodBar1.png",
        "smoothed": true,
        "userAdded": true
      },
      {
        "alwaysLoaded": false,
        "file": "FoodBar2.png",
        "kind": "image",
        "metadata": "",
        "name": "FoodBar2.png",
        "smoothed": true,
        "userAdded": true
      },
      {
        "alwaysLoaded": false,
        "file": "FoodBar3.png",
        "kind": "image",
        "metadata": "",
        "name": "FoodBar3.png",
        "smoothed": true,
        "userAdded": true
      },
      {
        "alwaysLoaded": false,
        "file": "FoodBar4.png",
        "kind": "image",
        "metadata": "",
        "name": "FoodBar4.png",
        "smoothed": true,
        "userAdded": true
      },
      {
        "alwaysLoaded": false,
        "file": "FullFoodBar.png",
        "kind": "image",
        "metadata": "",
        "name": "FullFoodBar.png",
        "smoothed": true,
        "userAdded": true
      },
      {
        "alwaysLoaded": false,
        "file": "New Piskel-1.png.png",
        "kind": "image",
        "metadata": "",
        "name": "New Piskel-1.png.png",
        "smoothed": true,
        "userAdded": true
      },
      {
        "alwaysLoaded": false,
        "file": "New Piskel-2.png.png",
        "kind": "image",
        "metadata": "",
        "name": "New Piskel-2.png.png",
        "smoothed": true,
        "userAdded": true
      },
      {
        "alwaysLoaded": false,
        "file": "NewObject-1.png",
        "kind": "image",
        "metadata": "",
        "name": "NewObject-1.png",
        "smoothed": true,
        "userAdded": true
      },
      {
        "alwaysLoaded": false,
        "file": "NewObject-2.png",
        "kind": "image",
        "metadata": "",
        "name": "NewObject-2.png",
        "smoothed": true,
        "userAdded": true
      },
      {
        "alwaysLoaded": false,
        "file": "NewObject-3.png",
        "kind": "image",
        "metadata": "",
        "name": "NewObject-3.png",
        "smoothed": true,
        "userAdded": true
      },
      {
        "alwaysLoaded": false,
        "file": "NewObject-4.png",
        "kind": "image",
        "metadata": "",
        "name": "NewObject-4.png",
        "smoothed": true,
        "userAdded": true
      },
      {
        "alwaysLoaded": false,
        "file": "Fat-1-0.png",
        "kind": "image",
        "metadata": "",
        "name": "Fat-1-0.png",
        "smoothed": true,
        "userAdded": true
      },
      {
        "alwaysLoaded": false,
        "file": "Fat-2-0.png",
        "kind": "image",
        "metadata": "",
        "name": "Fat-2-0.png",
        "smoothed": true,
        "userAdded": true
      },
      {
        "alwaysLoaded": false,
        "file": "Fat-3-0.png",
        "kind": "image",
        "metadata": "",
        "name": "Fat-3-0.png",
        "smoothed": true,
        "userAdded": true
      },
      {
        "alwaysLoaded": false,
        "file": "Fat-4-0.png",
        "kind": "image",
        "metadata": "",
        "name": "Fat-4-0.png",
        "smoothed": true,
        "userAdded": true
      },
      {
        "alwaysLoaded": false,
        "file": "NewFile-1.png",
        "kind": "image",
        "metadata": "",
        "name": "NewFile-1.png",
        "smoothed": true,
        "userAdded": true
      },
      {
        "alwaysLoaded": false,
        "file": "NewFile-1-0.png",
        "kind": "image",
        "metadata": "",
        "name": "NewFile-1-0.png",
        "smoothed": true,
        "userAdded": true
      },
      {
        "alwaysLoaded": false,
        "file": "NewFile-1-1.png",
        "kind": "image",
        "metadata": "",
        "name": "NewFile-1-1.png",
        "smoothed": true,
        "userAdded": true
      },
      {
        "alwaysLoaded": false,
        "file": "NewFile-1-2.png",
        "kind": "image",
        "metadata": "",
        "name": "NewFile-1-2.png",
        "smoothed": true,
        "userAdded": true
      },
      {
        "alwaysLoaded": false,
        "file": "NormalWalk-1.png",
        "kind": "image",
        "metadata": "",
        "name": "NormalWalk-1.png",
        "smoothed": true,
        "userAdded": true
      },
      {
        "alwaysLoaded": false,
        "file": "NormalWalk-2.png",
        "kind": "image",
        "metadata": "",
        "name": "NormalWalk-2.png",
        "smoothed": true,
        "userAdded": true
      },
      {
        "alwaysLoaded": false,
        "file": "NormalWalk-3.png",
        "kind": "image",
        "metadata": "",
        "name": "NormalWalk-3.png",
        "smoothed": true,
        "userAdded": true
      },
      {
        "alwaysLoaded": false,
        "file": "NormalWalk-4.png",
        "kind": "image",
        "metadata": "",
        "name": "NormalWalk-4.png",
        "smoothed": true,
        "userAdded": true
      },
      {
        "alwaysLoaded": false,
        "file": "NormalWalk-5.png",
        "kind": "image",
        "metadata": "",
        "name": "NormalWalk-5.png",
        "smoothed": true,
        "userAdded": true
      },
      {
        "alwaysLoaded": false,
        "file": "NormalWalk-6.png",
        "kind": "image",
        "metadata": "",
        "name": "NormalWalk-6.png",
        "smoothed": true,
        "userAdded": true
      },
      {
        "alwaysLoaded": false,
        "file": "FatWalk-1.png",
        "kind": "image",
        "metadata": "",
        "name": "FatWalk-1.png",
        "smoothed": true,
        "userAdded": true
      },
      {
        "alwaysLoaded": false,
        "file": "FatWalk-2.png",
        "kind": "image",
        "metadata": "",
        "name": "FatWalk-2.png",
        "smoothed": true,
        "userAdded": true
      },
      {
        "alwaysLoaded": false,
        "file": "FatWalk-3.png",
        "kind": "image",
        "metadata": "",
        "name": "FatWalk-3.png",
        "smoothed": true,
        "userAdded": false
      },
      {
        "alwaysLoaded": false,
        "file": "FatWalk-4.png",
        "kind": "image",
        "metadata": "",
        "name": "FatWalk-4.png",
        "smoothed": true,
        "userAdded": false
      },
      {
        "alwaysLoaded": false,
        "file": "FatWalk-5.png",
        "kind": "image",
        "metadata": "",
        "name": "FatWalk-5.png",
        "smoothed": true,
        "userAdded": false
      },
      {
        "alwaysLoaded": false,
        "file": "FatWalk-1-0.png",
        "kind": "image",
        "metadata": "",
        "name": "FatWalk-1-0.png",
        "smoothed": true,
        "userAdded": true
      },
      {
        "alwaysLoaded": false,
        "file": "FatWalk-2-0.png",
        "kind": "image",
        "metadata": "",
        "name": "FatWalk-2-0.png",
        "smoothed": true,
        "userAdded": true
      },
      {
        "alwaysLoaded": false,
        "file": "FatWalk-3-0.png",
        "kind": "image",
        "metadata": "",
        "name": "FatWalk-3-0.png",
        "smoothed": true,
        "userAdded": true
      },
      {
        "alwaysLoaded": false,
        "file": "FatWalk-4-0.png",
        "kind": "image",
        "metadata": "",
        "name": "FatWalk-4-0.png",
        "smoothed": true,
        "userAdded": true
      },
      {
        "alwaysLoaded": false,
        "file": "FatWalk-5-0.png",
        "kind": "image",
        "metadata": "",
        "name": "FatWalk-5-0.png",
        "smoothed": true,
        "userAdded": true
      },
      {
        "alwaysLoaded": false,
        "file": "FatWalk-6.png",
        "kind": "image",
        "metadata": "",
        "name": "FatWalk-6.png",
        "smoothed": true,
        "userAdded": true
      },
      {
        "alwaysLoaded": false,
        "file": "Normal-1-0.png",
        "kind": "image",
        "metadata": "",
        "name": "Normal-1-0.png",
        "smoothed": true,
        "userAdded": true
      },
      {
        "alwaysLoaded": false,
        "file": "Normal-2-0.png",
        "kind": "image",
        "metadata": "",
        "name": "Normal-2-0.png",
        "smoothed": true,
        "userAdded": true
      },
      {
        "alwaysLoaded": false,
        "file": "Normal-3-0.png",
        "kind": "image",
        "metadata": "",
        "name": "Normal-3-0.png",
        "smoothed": true,
        "userAdded": true
      },
      {
        "alwaysLoaded": false,
        "file": "Normal-4-0.png",
        "kind": "image",
        "metadata": "",
        "name": "Normal-4-0.png",
        "smoothed": true,
        "userAdded": true
      },
      {
        "alwaysLoaded": false,
        "file": "Fat-1-1.png",
        "kind": "image",
        "metadata": "",
        "name": "Fat-1-1.png",
        "smoothed": true,
        "userAdded": true
      },
      {
        "alwaysLoaded": false,
        "file": "Fat-2-1.png",
        "kind": "image",
        "metadata": "",
        "name": "Fat-2-1.png",
        "smoothed": true,
        "userAdded": true
      },
      {
        "alwaysLoaded": false,
        "file": "Fat-3-1.png",
        "kind": "image",
        "metadata": "",
        "name": "Fat-3-1.png",
        "smoothed": true,
        "userAdded": true
      },
      {
        "alwaysLoaded": false,
        "file": "Fat-4-1.png",
        "kind": "image",
        "metadata": "",
        "name": "Fat-4-1.png",
        "smoothed": true,
        "userAdded": true
      },
      {
        "alwaysLoaded": false,
        "file": "ManWalkFat (1)-1.png.png",
        "kind": "image",
        "metadata": "",
        "name": "ManWalkFat (1)-1.png.png",
        "smoothed": true,
        "userAdded": true
      },
      {
        "alwaysLoaded": false,
        "file": "ManWalkFat1-1-1.png",
        "kind": "image",
        "metadata": "",
        "name": "ManWalkFat1-1-1.png",
        "smoothed": true,
        "userAdded": true
      },
      {
        "alwaysLoaded": false,
        "file": "IdleNormal-1.png",
        "kind": "image",
        "metadata": "",
        "name": "IdleNormal-1.png",
        "smoothed": true,
        "userAdded": true
      },
      {
        "alwaysLoaded": false,
        "file": "IdleNormal-2.png",
        "kind": "image",
        "metadata": "",
        "name": "IdleNormal-2.png",
        "smoothed": true,
        "userAdded": true
      },
      {
        "alwaysLoaded": false,
        "file": "IdleNormal-3.png",
        "kind": "image",
        "metadata": "",
        "name": "IdleNormal-3.png",
        "smoothed": true,
        "userAdded": true
      },
      {
        "alwaysLoaded": false,
        "file": "IdleNormal-4.png",
        "kind": "image",
        "metadata": "",
        "name": "IdleNormal-4.png",
        "smoothed": true,
        "userAdded": true
      },
      {
        "alwaysLoaded": false,
        "file": "ManWalk.png",
        "kind": "image",
        "metadata": "",
        "name": "ManWalk.png",
        "smoothed": true,
        "userAdded": true
      },
      {
        "alwaysLoaded": false,
        "file": "Walk-1.png",
        "kind": "image",
        "metadata": "",
        "name": "Walk-1.png",
        "smoothed": true,
        "userAdded": false
      },
      {
        "alwaysLoaded": false,
        "file": "Walk-2.png",
        "kind": "image",
        "metadata": "",
        "name": "Walk-2.png",
        "smoothed": true,
        "userAdded": false
      },
      {
        "alwaysLoaded": false,
        "file": "Walk-3.png",
        "kind": "image",
        "metadata": "",
        "name": "Walk-3.png",
        "smoothed": true,
        "userAdded": false
      },
      {
        "alwaysLoaded": false,
        "file": "Walk-4.png",
        "kind": "image",
        "metadata": "",
        "name": "Walk-4.png",
        "smoothed": true,
        "userAdded": false
      },
      {
        "alwaysLoaded": false,
        "file": "Walk-5.png",
        "kind": "image",
        "metadata": "",
        "name": "Walk-5.png",
        "smoothed": true,
        "userAdded": false
      },
      {
        "alwaysLoaded": false,
        "file": "Walk-6.png",
        "kind": "image",
        "metadata": "",
        "name": "Walk-6.png",
        "smoothed": true,
        "userAdded": false
      },
      {
        "alwaysLoaded": false,
        "file": "NewObject-1-0.png",
        "kind": "image",
        "metadata": "",
        "name": "NewObject-1-0.png",
        "smoothed": true,
        "userAdded": true
      },
      {
        "alwaysLoaded": false,
        "file": "NewObject-2-0.png",
        "kind": "image",
        "metadata": "",
        "name": "NewObject-2-0.png",
        "smoothed": true,
        "userAdded": true
      },
      {
        "alwaysLoaded": false,
        "file": "NewObject-3-0.png",
        "kind": "image",
        "metadata": "",
        "name": "NewObject-3-0.png",
        "smoothed": true,
        "userAdded": true
      },
      {
        "alwaysLoaded": false,
        "file": "NewObject-4-0.png",
        "kind": "image",
        "metadata": "",
        "name": "NewObject-4-0.png",
        "smoothed": true,
        "userAdded": true
      },
      {
        "alwaysLoaded": false,
        "file": "WalkFat-1.png",
        "kind": "image",
        "metadata": "",
        "name": "WalkFat-1.png",
        "smoothed": true,
        "userAdded": true
      },
      {
        "alwaysLoaded": false,
        "file": "WalkFat-2.png",
        "kind": "image",
        "metadata": "",
        "name": "WalkFat-2.png",
        "smoothed": true,
        "userAdded": true
      },
      {
        "alwaysLoaded": false,
        "file": "WalkFat-3.png",
        "kind": "image",
        "metadata": "",
        "name": "WalkFat-3.png",
        "smoothed": true,
        "userAdded": true
      },
      {
        "alwaysLoaded": false,
        "file": "WalkFat-4.png",
        "kind": "image",
        "metadata": "",
        "name": "WalkFat-4.png",
        "smoothed": true,
        "userAdded": true
      },
      {
        "alwaysLoaded": false,
        "file": "WalkFat-5.png",
        "kind": "image",
        "metadata": "",
        "name": "WalkFat-5.png",
        "smoothed": true,
        "userAdded": true
      },
      {
        "alwaysLoaded": false,
        "file": "WalkFat-6.png",
        "kind": "image",
        "metadata": "",
        "name": "WalkFat-6.png",
        "smoothed": true,
        "userAdded": true
      },
      {
        "alwaysLoaded": false,
        "file": "NewObject-1-1.png",
        "kind": "image",
        "metadata": "",
        "name": "NewObject-1-1.png",
        "smoothed": true,
        "userAdded": true
      },
      {
        "alwaysLoaded": false,
        "file": "NewObject-1-2.png",
        "kind": "image",
        "metadata": "",
        "name": "NewObject-1-2.png",
        "smoothed": true,
        "userAdded": true
      },
      {
        "alwaysLoaded": false,
        "file": "IdleNormal-1-0.png",
        "kind": "image",
        "metadata": "",
        "name": "IdleNormal-1-0.png",
        "smoothed": true,
        "userAdded": true
      },
      {
        "alwaysLoaded": false,
        "file": "IdleNormal-2-0.png",
        "kind": "image",
        "metadata": "",
        "name": "IdleNormal-2-0.png",
        "smoothed": true,
        "userAdded": true
      },
      {
        "alwaysLoaded": false,
        "file": "IdleNormal-3-0.png",
        "kind": "image",
        "metadata": "",
        "name": "IdleNormal-3-0.png",
        "smoothed": true,
        "userAdded": true
      },
      {
        "alwaysLoaded": false,
        "file": "IdleNormal-4-0.png",
        "kind": "image",
        "metadata": "",
        "name": "IdleNormal-4-0.png",
        "smoothed": true,
        "userAdded": true
      },
      {
        "alwaysLoaded": false,
        "file": "NewObject-1-3.png",
        "kind": "image",
        "metadata": "",
        "name": "NewObject-1-3.png",
        "smoothed": true,
        "userAdded": true
      },
      {
        "alwaysLoaded": false,
        "file": "NewObject-1-4.png",
        "kind": "image",
        "metadata": "",
        "name": "NewObject-1-4.png",
        "smoothed": true,
        "userAdded": false
      },
      {
        "alwaysLoaded": false,
        "file": "NewObject-1-5.png",
        "kind": "image",
        "metadata": "",
        "name": "NewObject-1-5.png",
        "smoothed": true,
        "userAdded": true
      },
      {
        "alwaysLoaded": false,
        "file": "Escada-1.png",
        "kind": "image",
        "metadata": "",
        "name": "Escada-1.png",
        "smoothed": true,
        "userAdded": true
      },
      {
        "alwaysLoaded": false,
        "file": "NewObject-1-6.png",
        "kind": "image",
        "metadata": "",
        "name": "NewObject-1-6.png",
        "smoothed": true,
        "userAdded": true
      },
      {
        "alwaysLoaded": false,
        "file": "NewFile-1-3.png",
        "kind": "image",
        "metadata": "",
        "name": "NewFile-1-3.png",
        "smoothed": true,
        "userAdded": true
      },
      {
        "alwaysLoaded": false,
        "file": "NewFile-1-4.png",
        "kind": "image",
        "metadata": "",
        "name": "NewFile-1-4.png",
        "smoothed": true,
        "userAdded": true
      }
    ],
    "resourceFolders": []
  },
  "objects": [],
  "objectsGroups": [],
  "variables": [],
  "layouts": [
    {
      "b": 209,
      "disableInputWhenNotFocused": true,
      "mangledName": "Menu",
      "name": "Menu",
      "oglFOV": 90,
      "oglZFar": 500,
      "oglZNear": 1,
      "r": 209,
      "standardSortMethod": true,
      "stopSoundsOnStartup": true,
      "title": "",
      "v": 209,
      "uiSettings": {
        "grid": false,
        "gridB": 255,
        "gridG": 180,
        "gridHeight": 32,
        "gridOffsetX": 0,
        "gridOffsetY": 0,
        "gridR": 158,
        "gridWidth": 32,
        "snap": true,
        "windowMask": false,
        "zoomFactor": 1
      },
      "objectsGroups": [],
      "variables": [],
      "instances": [],
      "objects": [],
      "events": [],
      "layers": [
        {
          "name": "",
          "visibility": true,
          "cameras": [
            {
              "defaultSize": true,
              "defaultViewport": true,
              "height": 0,
              "viewportBottom": 1,
              "viewportLeft": 0,
              "viewportRight": 1,
              "viewportTop": 0,
              "width": 0
            }
          ],
          "effects": []
        }
      ],
      "behaviorsSharedData": []
    },
    {
      "b": 209,
      "disableInputWhenNotFocused": true,
      "mangledName": "Game",
      "name": "Game",
      "oglFOV": 90,
      "oglZFar": 500,
      "oglZNear": 1,
      "r": 209,
      "standardSortMethod": true,
      "stopSoundsOnStartup": true,
      "title": "",
      "v": 209,
      "uiSettings": {
        "grid": true,
        "gridB": 255,
        "gridG": 180,
        "gridHeight": 32,
        "gridOffsetX": 0,
        "gridOffsetY": 0,
        "gridR": 158,
        "gridWidth": 32,
        "snap": true,
        "windowMask": false,
        "zoomFactor": 1.144
      },
      "objectsGroups": [],
      "variables": [],
      "instances": [
        {
          "angle": 0,
          "customSize": true,
          "height": 32,
          "layer": "Jogo",
          "locked": false,
          "name": "Chao",
          "width": 640,
          "x": 0,
          "y": 288,
          "zOrder": 4,
          "numberProperties": [],
          "stringProperties": [],
          "initialVariables": []
        },
        {
          "angle": 0,
          "customSize": true,
          "height": 320,
          "layer": "Jogo",
          "locked": false,
          "name": "Parede",
          "width": 32,
          "x": 0,
          "y": 0,
          "zOrder": 5,
          "numberProperties": [],
          "stringProperties": [],
          "initialVariables": []
        },
        {
          "angle": 0,
          "customSize": true,
          "height": 320,
          "layer": "Jogo",
          "locked": false,
          "name": "Parede",
          "width": 32,
          "x": 608,
          "y": 0,
          "zOrder": 5,
          "numberProperties": [],
          "stringProperties": [],
          "initialVariables": []
        },
        {
          "angle": 0,
          "customSize": true,
          "height": 32,
          "layer": "Jogo",
          "locked": false,
          "name": "Chao",
          "width": 256,
          "x": 32,
          "y": 160,
          "zOrder": 6,
          "numberProperties": [],
          "stringProperties": [],
          "initialVariables": []
        },
        {
          "angle": 0,
          "customSize": true,
          "height": 32,
          "layer": "Jogo",
          "locked": false,
          "name": "Teto",
          "width": 640,
          "x": 0,
          "y": 0,
          "zOrder": 7,
          "numberProperties": [],
          "stringProperties": [],
          "initialVariables": []
        },
        {
          "angle": 0,
          "customSize": true,
          "height": 320,
          "layer": "Fundo",
          "locked": false,
          "name": "Fundo",
          "width": 640,
          "x": 0,
          "y": -224,
          "zOrder": 8,
          "numberProperties": [],
          "stringProperties": [],
          "initialVariables": []
        },
        {
          "angle": 0,
          "customSize": false,
          "height": 0,
          "layer": "Jogo",
          "locked": false,
          "name": "PlayerHitBox",
          "width": 0,
          "x": 416,
          "y": 160,
          "zOrder": 9,
          "numberProperties": [],
          "stringProperties": [],
          "initialVariables": []
        },
        {
          "angle": 0,
          "customSize": false,
          "height": 0,
          "layer": "Jogo",
          "locked": false,
          "name": "SkinNormal",
          "width": 0,
          "x": 320,
          "y": 192,
          "zOrder": 10,
          "numberProperties": [],
          "stringProperties": [],
          "initialVariables": []
        },
        {
          "angle": 0,
          "customSize": false,
          "height": 0,
          "layer": "Jogo",
          "locked": false,
          "name": "SkinFat",
          "width": 0,
          "x": 448,
          "y": 192,
          "zOrder": 11,
          "numberProperties": [],
          "stringProperties": [],
          "initialVariables": []
        },
        {
          "angle": 0,
          "customSize": false,
          "height": 0,
          "layer": "Jogo",
          "locked": false,
          "name": "Fogao",
          "width": 0,
          "x": 512,
          "y": 256,
          "zOrder": 12,
          "numberProperties": [],
          "stringProperties": [],
          "initialVariables": []
        },
        {
          "angle": 0,
          "customSize": false,
          "height": 0,
          "layer": "Jogo",
          "locked": false,
          "name": "Peso",
          "width": 0,
          "x": 64,
          "y": 256,
          "zOrder": 13,
          "numberProperties": [],
          "stringProperties": [],
          "initialVariables": []
        },
        {
          "angle": 0,
          "customSize": false,
          "height": 0,
          "layer": "Jogo",
          "locked": false,
          "name": "Cama",
          "width": 0,
          "x": 512,
          "y": 128,
          "zOrder": 15,
          "numberProperties": [],
          "stringProperties": [],
          "initialVariables": []
        },
        {
          "angle": 0,
          "customSize": false,
          "height": 0,
          "layer": "Variaveis(Barras)",
          "locked": false,
          "name": "NewObject",
          "width": 0,
          "x": 0,
          "y": 0,
          "zOrder": 16,
          "numberProperties": [],
          "stringProperties": [],
          "initialVariables": []
        },
        {
          "angle": 0,
          "customSize": true,
          "height": 64,
          "layer": "Variaveis(Barras)",
          "locked": false,
          "name": "FoodBar",
          "width": 64,
          "x": 0,
          "y": 0,
          "zOrder": 17,
          "numberProperties": [],
          "stringProperties": [],
          "initialVariables": []
        },
        {
          "angle": 0,
          "customSize": true,
          "height": 32,
          "layer": "",
          "locked": false,
          "name": "Chao",
          "width": 224,
          "x": 384,
          "y": 160,
          "zOrder": 20,
          "numberProperties": [],
          "stringProperties": [],
          "initialVariables": []
        }
      ],
      "objects": [
        {
          "name": "FoodBar",
          "tags": "",
          "type": "Sprite",
          "updateIfNotVisible": false,
          "variables": [],
          "behaviors": [],
          "animations": [
            {
              "name": "One",
              "useMultipleDirections": false,
              "directions": [
                {
                  "looping": false,
                  "timeBetweenFrames": 0.08,
                  "sprites": [
                    {
                      "hasCustomCollisionMask": false,
                      "image": "FoodBar1.png",
                      "points": [],
                      "originPoint": {
                        "name": "origine",
                        "x": 0,
                        "y": 0
                      },
                      "centerPoint": {
                        "automatic": true,
                        "name": "centre",
                        "x": 0,
                        "y": 0
                      },
                      "customCollisionMask": []
                    }
                  ]
                }
              ]
            },
            {
              "name": "Two",
              "useMultipleDirections": false,
              "directions": [
                {
                  "looping": false,
                  "timeBetweenFrames": 0.08,
                  "sprites": [
                    {
                      "hasCustomCollisionMask": false,
                      "image": "FoodBar2.png",
                      "points": [],
                      "originPoint": {
                        "name": "origine",
                        "x": 0,
                        "y": 0
                      },
                      "centerPoint": {
                        "automatic": true,
                        "name": "centre",
                        "x": 0,
                        "y": 0
                      },
                      "customCollisionMask": []
                    }
                  ]
                }
              ]
            },
            {
              "name": "Three",
              "useMultipleDirections": false,
              "directions": [
                {
                  "looping": false,
                  "timeBetweenFrames": 0.08,
                  "sprites": [
                    {
                      "hasCustomCollisionMask": false,
                      "image": "FoodBar3.png",
                      "points": [],
                      "originPoint": {
                        "name": "origine",
                        "x": 0,
                        "y": 0
                      },
                      "centerPoint": {
                        "automatic": true,
                        "name": "centre",
                        "x": 0,
                        "y": 0
                      },
                      "customCollisionMask": []
                    }
                  ]
                }
              ]
            },
            {
              "name": "Four",
              "useMultipleDirections": false,
              "directions": [
                {
                  "looping": false,
                  "timeBetweenFrames": 0.08,
                  "sprites": [
                    {
                      "hasCustomCollisionMask": false,
                      "image": "FoodBar4.png",
                      "points": [],
                      "originPoint": {
                        "name": "origine",
                        "x": 0,
                        "y": 0
                      },
                      "centerPoint": {
                        "automatic": true,
                        "name": "centre",
                        "x": 0,
                        "y": 0
                      },
                      "customCollisionMask": []
                    }
                  ]
                }
              ]
            },
            {
              "name": "Full",
              "useMultipleDirections": false,
              "directions": [
                {
                  "looping": false,
                  "timeBetweenFrames": 0.08,
                  "sprites": [
                    {
                      "hasCustomCollisionMask": false,
                      "image": "FullFoodBar.png",
                      "points": [],
                      "originPoint": {
                        "name": "origine",
                        "x": 0,
                        "y": 0
                      },
                      "centerPoint": {
                        "automatic": true,
                        "name": "centre",
                        "x": 0,
                        "y": 0
                      },
                      "customCollisionMask": []
                    }
                  ]
                }
              ]
            }
          ]
        },
        {
          "height": 32,
          "name": "Chao",
          "tags": "",
          "texture": "NewFile-1.png",
          "type": "TiledSpriteObject::TiledSprite",
          "width": 32,
          "variables": [],
          "behaviors": [
            {
              "name": "Platform",
              "platformType": "NormalPlatform",
              "type": "PlatformBehavior::PlatformBehavior",
              "canBeGrabbed": true,
              "yGrabOffset": 0
            }
          ]
        },
        {
          "height": 32,
          "name": "Parede",
          "tags": "",
          "texture": "NewFile-1-0.png",
          "type": "TiledSpriteObject::TiledSprite",
          "width": 32,
          "variables": [],
          "behaviors": [
            {
              "canBeGrabbed": true,
              "name": "Platform",
              "platformType": "NormalPlatform",
              "type": "PlatformBehavior::PlatformBehavior",
              "yGrabOffset": 0
            }
          ]
        },
        {
          "height": 32,
          "name": "Teto",
          "tags": "",
          "texture": "NewFile-1-1.png",
          "type": "TiledSpriteObject::TiledSprite",
          "width": 32,
          "variables": [],
          "behaviors": [
            {
              "canBeGrabbed": true,
              "name": "Platform",
              "platformType": "NormalPlatform",
              "type": "PlatformBehavior::PlatformBehavior",
              "yGrabOffset": 0
            }
          ]
        },
        {
          "height": 32,
          "name": "Fundo",
          "tags": "",
          "texture": "NewFile-1-2.png",
          "type": "TiledSpriteObject::TiledSprite",
          "width": 32,
          "variables": [],
          "behaviors": []
        },
        {
          "name": "PlayerHitBox",
          "tags": "",
          "type": "Sprite",
          "updateIfNotVisible": false,
          "variables": [
            {
              "name": "Gordura",
              "value": "1"
            }
          ],
          "behaviors": [
            {
              "acceleration": 1500,
              "canGrabPlatforms": false,
              "deceleration": 1500,
              "gravity": 1000,
              "ignoreDefaultControls": true,
              "jumpSpeed": 600,
              "jumpSustainTime": 0.2,
              "maxFallingSpeed": 700,
              "maxSpeed": 200,
              "name": "PlatformerObject",
              "roundCoordinates": true,
              "slopeMaxAngle": 60,
              "type": "PlatformBehavior::PlatformerObjectBehavior",
              "xGrabTolerance": 10,
              "yGrabOffset": 0
            }
          ],
          "animations": [
            {
              "name": "HitBox",
              "useMultipleDirections": false,
              "directions": [
                {
                  "looping": false,
                  "timeBetweenFrames": 0.08,
                  "sprites": [
                    {
                      "hasCustomCollisionMask": true,
                      "image": "ManWalkFat1-1-1.png",
                      "points": [],
                      "originPoint": {
                        "name": "origine",
                        "x": 0,
                        "y": 0
                      },
                      "centerPoint": {
                        "automatic": true,
                        "name": "centre",
                        "x": 0,
                        "y": 0
                      },
                      "customCollisionMask": [
                        [
                          {
                            "x": 6.7,
                            "y": 13
                          },
                          {
                            "x": 29.9095,
                            "y": 13
                          },
                          {
                            "x": 29.9095,
                            "y": 47.5
                          },
                          {
                            "x": 6.7,
                            "y": 47.5
                          }
                        ]
                      ]
                    }
                  ]
                }
              ]
            }
          ]
        },
        {
          "name": "SkinNormal",
          "tags": "",
          "type": "Sprite",
          "updateIfNotVisible": false,
          "variables": [],
          "behaviors": [],
          "animations": [
            {
              "name": "IdleNormal",
              "useMultipleDirections": false,
              "directions": [
                {
                  "looping": true,
                  "timeBetweenFrames": 0.0833,
                  "sprites": [
                    {
                      "hasCustomCollisionMask": false,
                      "image": "IdleNormal-1-0.png",
                      "points": [],
                      "originPoint": {
                        "name": "origine",
                        "x": 0,
                        "y": 0
                      },
                      "centerPoint": {
                        "automatic": true,
                        "name": "centre",
                        "x": 0,
                        "y": 0
                      },
                      "customCollisionMask": []
                    },
                    {
                      "hasCustomCollisionMask": false,
                      "image": "IdleNormal-2-0.png",
                      "points": [],
                      "originPoint": {
                        "name": "origine",
                        "x": 0,
                        "y": 0
                      },
                      "centerPoint": {
                        "automatic": true,
                        "name": "centre",
                        "x": 0,
                        "y": 0
                      },
                      "customCollisionMask": []
                    },
                    {
                      "hasCustomCollisionMask": false,
                      "image": "IdleNormal-3-0.png",
                      "points": [],
                      "originPoint": {
                        "name": "origine",
                        "x": 0,
                        "y": 0
                      },
                      "centerPoint": {
                        "automatic": true,
                        "name": "centre",
                        "x": 0,
                        "y": 0
                      },
                      "customCollisionMask": []
                    },
                    {
                      "hasCustomCollisionMask": false,
                      "image": "IdleNormal-4-0.png",
                      "points": [],
                      "originPoint": {
                        "name": "origine",
                        "x": 0,
                        "y": 0
                      },
                      "centerPoint": {
                        "automatic": true,
                        "name": "centre",
                        "x": 0,
                        "y": 0
                      },
                      "customCollisionMask": []
                    }
                  ]
                }
              ]
            },
            {
              "name": "Walk",
              "useMultipleDirections": false,
              "directions": [
                {
                  "looping": true,
                  "timeBetweenFrames": 0.0833,
                  "sprites": [
                    {
                      "hasCustomCollisionMask": false,
                      "image": "Walk-1.png",
                      "points": [],
                      "originPoint": {
                        "name": "origine",
                        "x": 0,
                        "y": 0
                      },
                      "centerPoint": {
                        "automatic": true,
                        "name": "centre",
                        "x": 0,
                        "y": 0
                      },
                      "customCollisionMask": []
                    },
                    {
                      "hasCustomCollisionMask": false,
                      "image": "Walk-2.png",
                      "points": [],
                      "originPoint": {
                        "name": "origine",
                        "x": 0,
                        "y": 0
                      },
                      "centerPoint": {
                        "automatic": true,
                        "name": "centre",
                        "x": 0,
                        "y": 0
                      },
                      "customCollisionMask": []
                    },
                    {
                      "hasCustomCollisionMask": false,
                      "image": "Walk-3.png",
                      "points": [],
                      "originPoint": {
                        "name": "origine",
                        "x": 0,
                        "y": 0
                      },
                      "centerPoint": {
                        "automatic": true,
                        "name": "centre",
                        "x": 0,
                        "y": 0
                      },
                      "customCollisionMask": []
                    },
                    {
                      "hasCustomCollisionMask": false,
                      "image": "Walk-4.png",
                      "points": [],
                      "originPoint": {
                        "name": "origine",
                        "x": 0,
                        "y": 0
                      },
                      "centerPoint": {
                        "automatic": true,
                        "name": "centre",
                        "x": 0,
                        "y": 0
                      },
                      "customCollisionMask": []
                    },
                    {
                      "hasCustomCollisionMask": false,
                      "image": "Walk-5.png",
                      "points": [],
                      "originPoint": {
                        "name": "origine",
                        "x": 0,
                        "y": 0
                      },
                      "centerPoint": {
                        "automatic": true,
                        "name": "centre",
                        "x": 0,
                        "y": 0
                      },
                      "customCollisionMask": []
                    },
                    {
                      "hasCustomCollisionMask": false,
                      "image": "Walk-6.png",
                      "points": [],
                      "originPoint": {
                        "name": "origine",
                        "x": 0,
                        "y": 0
                      },
                      "centerPoint": {
                        "automatic": true,
                        "name": "centre",
                        "x": 0,
                        "y": 0
                      },
                      "customCollisionMask": []
                    }
                  ]
                }
              ]
            }
          ]
        },
        {
          "name": "SkinFat",
          "tags": "",
          "type": "Sprite",
          "updateIfNotVisible": false,
          "variables": [],
          "behaviors": [],
          "animations": [
            {
              "name": "IdleFat",
              "useMultipleDirections": false,
              "directions": [
                {
                  "looping": true,
                  "timeBetweenFrames": 0.1667,
                  "sprites": [
                    {
                      "hasCustomCollisionMask": false,
                      "image": "NewObject-1-0.png",
                      "points": [],
                      "originPoint": {
                        "name": "origine",
                        "x": 0,
                        "y": 0
                      },
                      "centerPoint": {
                        "automatic": true,
                        "name": "centre",
                        "x": 0,
                        "y": 0
                      },
                      "customCollisionMask": []
                    },
                    {
                      "hasCustomCollisionMask": false,
                      "image": "NewObject-2-0.png",
                      "points": [],
                      "originPoint": {
                        "name": "origine",
                        "x": 0,
                        "y": 0
                      },
                      "centerPoint": {
                        "automatic": true,
                        "name": "centre",
                        "x": 0,
                        "y": 0
                      },
                      "customCollisionMask": []
                    },
                    {
                      "hasCustomCollisionMask": false,
                      "image": "NewObject-3-0.png",
                      "points": [],
                      "originPoint": {
                        "name": "origine",
                        "x": 0,
                        "y": 0
                      },
                      "centerPoint": {
                        "automatic": true,
                        "name": "centre",
                        "x": 0,
                        "y": 0
                      },
                      "customCollisionMask": []
                    },
                    {
                      "hasCustomCollisionMask": false,
                      "image": "NewObject-4-0.png",
                      "points": [],
                      "originPoint": {
                        "name": "origine",
                        "x": 0,
                        "y": 0
                      },
                      "centerPoint": {
                        "automatic": true,
                        "name": "centre",
                        "x": 0,
                        "y": 0
                      },
                      "customCollisionMask": []
                    }
                  ]
                }
              ]
            },
            {
              "name": "WalkFat",
              "useMultipleDirections": false,
              "directions": [
                {
                  "looping": true,
                  "timeBetweenFrames": 0.1667,
                  "sprites": [
                    {
                      "hasCustomCollisionMask": false,
                      "image": "WalkFat-1.png",
                      "points": [],
                      "originPoint": {
                        "name": "origine",
                        "x": 0,
                        "y": 0
                      },
                      "centerPoint": {
                        "automatic": true,
                        "name": "centre",
                        "x": 0,
                        "y": 0
                      },
                      "customCollisionMask": []
                    },
                    {
                      "hasCustomCollisionMask": false,
                      "image": "WalkFat-2.png",
                      "points": [],
                      "originPoint": {
                        "name": "origine",
                        "x": 0,
                        "y": 0
                      },
                      "centerPoint": {
                        "automatic": true,
                        "name": "centre",
                        "x": 0,
                        "y": 0
                      },
                      "customCollisionMask": []
                    },
                    {
                      "hasCustomCollisionMask": false,
                      "image": "WalkFat-3.png",
                      "points": [],
                      "originPoint": {
                        "name": "origine",
                        "x": 0,
                        "y": 0
                      },
                      "centerPoint": {
                        "automatic": true,
                        "name": "centre",
                        "x": 0,
                        "y": 0
                      },
                      "customCollisionMask": []
                    },
                    {
                      "hasCustomCollisionMask": false,
                      "image": "WalkFat-4.png",
                      "points": [],
                      "originPoint": {
                        "name": "origine",
                        "x": 0,
                        "y": 0
                      },
                      "centerPoint": {
                        "automatic": true,
                        "name": "centre",
                        "x": 0,
                        "y": 0
                      },
                      "customCollisionMask": []
                    },
                    {
                      "hasCustomCollisionMask": false,
                      "image": "WalkFat-5.png",
                      "points": [],
                      "originPoint": {
                        "name": "origine",
                        "x": 0,
                        "y": 0
                      },
                      "centerPoint": {
                        "automatic": true,
                        "name": "centre",
                        "x": 0,
                        "y": 0
                      },
                      "customCollisionMask": []
                    },
                    {
                      "hasCustomCollisionMask": false,
                      "image": "WalkFat-6.png",
                      "points": [],
                      "originPoint": {
                        "name": "origine",
                        "x": 0,
                        "y": 0
                      },
                      "centerPoint": {
                        "automatic": true,
                        "name": "centre",
                        "x": 0,
                        "y": 0
                      },
                      "customCollisionMask": []
                    }
                  ]
                }
              ]
            }
          ]
        },
        {
          "name": "Fogao",
          "tags": "",
          "type": "Sprite",
          "updateIfNotVisible": false,
          "variables": [],
          "behaviors": [],
          "animations": [
            {
              "name": "NewObject",
              "useMultipleDirections": false,
              "directions": [
                {
                  "looping": false,
                  "timeBetweenFrames": 0.08,
                  "sprites": [
                    {
                      "hasCustomCollisionMask": false,
                      "image": "NewObject-1-4.png",
                      "points": [],
                      "originPoint": {
                        "name": "origine",
                        "x": 0,
                        "y": 0
                      },
                      "centerPoint": {
                        "automatic": true,
                        "name": "centre",
                        "x": 0,
                        "y": 0
                      },
                      "customCollisionMask": []
                    }
                  ]
                }
              ]
            }
          ]
        },
        {
          "name": "Peso",
          "tags": "",
          "type": "Sprite",
          "updateIfNotVisible": false,
          "variables": [],
          "behaviors": [],
          "animations": [
            {
              "name": "NewObject",
              "useMultipleDirections": false,
              "directions": [
                {
                  "looping": false,
                  "timeBetweenFrames": 0.08,
                  "sprites": [
                    {
                      "hasCustomCollisionMask": false,
                      "image": "NewObject-1-5.png",
                      "points": [],
                      "originPoint": {
                        "name": "origine",
                        "x": 0,
                        "y": 0
                      },
                      "centerPoint": {
                        "automatic": true,
                        "name": "centre",
                        "x": 0,
                        "y": 0
                      },
                      "customCollisionMask": []
                    }
                  ]
                }
              ]
            }
          ]
        },
        {
          "name": "Cama",
          "tags": "",
          "type": "Sprite",
          "updateIfNotVisible": false,
          "variables": [],
          "behaviors": [],
          "animations": [
            {
              "name": "NewObject",
              "useMultipleDirections": false,
              "directions": [
                {
                  "looping": false,
                  "timeBetweenFrames": 0.08,
                  "sprites": [
                    {
                      "hasCustomCollisionMask": false,
                      "image": "NewObject-1-6.png",
                      "points": [],
                      "originPoint": {
                        "name": "origine",
                        "x": 0,
                        "y": 0
                      },
                      "centerPoint": {
                        "automatic": true,
                        "name": "centre",
                        "x": 0,
                        "y": 0
                      },
                      "customCollisionMask": []
                    }
                  ]
                }
              ]
            }
          ]
        },
        {
          "height": 64,
          "name": "NewObject",
          "tags": "",
          "texture": "NewFile-1-3.png",
          "type": "TiledSpriteObject::TiledSprite",
          "width": 640,
          "variables": [],
          "behaviors": []
        },
        {
          "name": "HappyBar",
          "tags": "",
          "type": "Sprite",
          "updateIfNotVisible": false,
          "variables": [],
          "behaviors": [],
          "animations": [
            {
              "name": "One",
              "useMultipleDirections": false,
              "directions": [
                {
                  "looping": false,
                  "timeBetweenFrames": 0.08,
                  "sprites": []
                }
              ]
            },
            {
              "name": "Two",
              "useMultipleDirections": false,
              "directions": [
                {
                  "looping": false,
                  "timeBetweenFrames": 0.08,
                  "sprites": []
                }
              ]
            },
            {
              "name": "Three",
              "useMultipleDirections": false,
              "directions": [
                {
                  "looping": false,
                  "timeBetweenFrames": 0.08,
                  "sprites": []
                }
              ]
            },
            {
              "name": "Four",
              "useMultipleDirections": false,
              "directions": [
                {
                  "looping": false,
                  "timeBetweenFrames": 0.08,
                  "sprites": []
                }
              ]
            },
            {
              "name": "Full",
              "useMultipleDirections": false,
              "directions": [
                {
                  "looping": false,
                  "timeBetweenFrames": 0.08,
                  "sprites": []
                }
              ]
            }
          ]
        }
      ],
      "events": [
        {
          "disabled": false,
          "folded": false,
          "type": "BuiltinCommonInstructions::Comment",
          "color": {
            "b": 109,
            "g": 230,
            "r": 255,
            "textB": 0,
            "textG": 0,
            "textR": 0
          },
          "comment": "Codigo",
          "comment2": ""
        },
        {
          "disabled": false,
          "folded": false,
          "type": "BuiltinCommonInstructions::Link",
          "include": {
            "includeConfig": 0
          },
          "target": "Player"
        }
      ],
      "layers": [
        {
          "name": "",
          "visibility": true,
          "cameras": [
            {
              "defaultSize": true,
              "defaultViewport": true,
              "height": 0,
              "viewportBottom": 1,
              "viewportLeft": 0,
              "viewportRight": 1,
              "viewportTop": 0,
              "width": 0
            }
          ],
          "effects": []
        },
        {
          "name": "Fundo",
          "visibility": true,
          "cameras": [],
          "effects": []
        },
        {
          "name": "Jogo",
          "visibility": true,
          "cameras": [],
          "effects": []
        },
        {
          "name": "Variaveis(Barras)",
          "visibility": true,
          "cameras": [],
          "effects": []
        }
      ],
      "behaviorsSharedData": [
        {
          "name": "Platform",
          "type": "PlatformBehavior::PlatformBehavior"
        },
        {
          "name": "PlatformerObject",
          "type": "PlatformBehavior::PlatformerObjectBehavior"
        }
      ]
    }
  ],
  "externalEvents": [
    {
      "associatedLayout": "Game",
      "lastChangeTimeStamp": 0,
      "name": "Player",
      "events": [
        {
          "disabled": false,
          "folded": false,
          "type": "BuiltinCommonInstructions::Standard",
          "conditions": [
            {
              "type": {
                "inverted": false,
                "value": "DepartScene"
              },
              "parameters": [
                ""
              ],
              "subInstructions": []
            }
          ],
          "actions": [
            {
              "type": {
                "inverted": false,
                "value": "UnPauseTimer"
              },
              "parameters": [
                "",
                "\"interaction\""
              ],
              "subInstructions": []
            }
          ],
          "events": []
        },
        {
          "disabled": false,
          "folded": false,
          "type": "BuiltinCommonInstructions::Comment",
          "color": {
            "b": 109,
            "g": 230,
            "r": 255,
            "textB": 0,
            "textG": 0,
            "textR": 0
          },
          "comment": "CreateSkinPlayer\n",
          "comment2": ""
        },
        {
          "disabled": false,
          "folded": false,
          "type": "BuiltinCommonInstructions::Standard",
          "conditions": [],
          "actions": [
            {
              "type": {
                "inverted": false,
                "value": "MettreXY"
              },
              "parameters": [
                "SkinNormal",
                "=",
                "PlayerHitBox.X()",
                "=",
                "PlayerHitBox.Y()"
              ],
              "subInstructions": []
            },
            {
              "type": {
                "inverted": false,
                "value": "MettreXY"
              },
              "parameters": [
                "SkinFat",
                "=",
                "PlayerHitBox.X()",
                "=",
                "PlayerHitBox.Y()"
              ],
              "subInstructions": []
            },
            {
              "type": {
                "inverted": false,
                "value": "Cache"
              },
              "parameters": [
                "PlayerHitBox"
              ],
              "subInstructions": []
            }
          ],
          "events": []
        },
        {
          "disabled": false,
          "folded": false,
          "type": "BuiltinCommonInstructions::Comment",
          "color": {
            "b": 109,
            "g": 230,
            "r": 255,
            "textB": 0,
            "textG": 0,
            "textR": 0
          },
          "comment": "PlayerComands",
          "comment2": ""
        },
        {
          "disabled": false,
          "folded": false,
          "type": "BuiltinCommonInstructions::Comment",
          "color": {
            "b": 109,
            "g": 230,
            "r": 255,
            "textB": 0,
            "textG": 0,
            "textR": 0
          },
          "comment": "Delay",
          "comment2": ""
        },
        {
          "disabled": false,
          "folded": false,
          "type": "BuiltinCommonInstructions::Standard",
          "conditions": [
            {
              "type": {
                "inverted": false,
                "value": "KeyPressed"
              },
              "parameters": [
                "",
                "Left"
              ],
              "subInstructions": []
            }
          ],
          "actions": [
            {
              "type": {
                "inverted": false,
                "value": "PlatformBehavior::SimulateLeftKey"
              },
              "parameters": [
                "PlayerHitBox",
                "PlatformerObject"
              ],
              "subInstructions": []
            },
            {
              "type": {
                "inverted": false,
                "value": "SetAnimationName"
              },
              "parameters": [
                "SkinNormal",
                "\"Walk\""
              ],
              "subInstructions": []
            },
            {
              "type": {
                "inverted": false,
                "value": "FlipX"
              },
              "parameters": [
                "SkinNormal",
                "yes"
              ],
              "subInstructions": []
            },
            {
              "type": {
                "inverted": false,
                "value": "FlipX"
              },
              "parameters": [
                "SkinFat",
                "yes"
              ],
              "subInstructions": []
            },
            {
              "type": {
                "inverted": false,
                "value": "SetAnimationName"
              },
              "parameters": [
                "SkinFat",
                "\"WalkFat\""
              ],
              "subInstructions": []
            }
          ],
          "events": []
        },
        {
          "disabled": false,
          "folded": false,
          "type": "BuiltinCommonInstructions::Standard",
          "conditions": [
            {
              "type": {
                "inverted": false,
                "value": "KeyPressed"
              },
              "parameters": [
                "",
                "Right"
              ],
              "subInstructions": []
            }
          ],
          "actions": [
            {
              "type": {
                "inverted": false,
                "value": "PlatformBehavior::SimulateRightKey"
              },
              "parameters": [
                "PlayerHitBox",
                "PlatformerObject"
              ],
              "subInstructions": []
            },
            {
              "type": {
                "inverted": false,
                "value": "FlipX"
              },
              "parameters": [
                "SkinNormal",
                "no"
              ],
              "subInstructions": []
            },
            {
              "type": {
                "inverted": false,
                "value": "SetAnimationName"
              },
              "parameters": [
                "SkinNormal",
                "\"Walk\""
              ],
              "subInstructions": []
            },
            {
              "type": {
                "inverted": false,
                "value": "SetAnimationName"
              },
              "parameters": [
                "SkinFat",
                "\"WalkFat\""
              ],
              "subInstructions": []
            },
            {
              "type": {
                "inverted": false,
                "value": "FlipX"
              },
              "parameters": [
                "SkinFat",
                "no"
              ],
              "subInstructions": []
            }
          ],
          "events": []
        },
        {
          "disabled": false,
          "folded": false,
          "type": "BuiltinCommonInstructions::Standard",
          "conditions": [
            {
              "type": {
                "inverted": true,
                "value": "PlatformBehavior::IsMoving"
              },
              "parameters": [
                "PlayerHitBox",
                "PlatformerObject"
              ],
              "subInstructions": []
            }
          ],
          "actions": [
            {
              "type": {
                "inverted": false,
                "value": "SetAnimationName"
              },
              "parameters": [
                "SkinNormal",
                "\"IdleNormal\""
              ],
              "subInstructions": []
            },
            {
              "type": {
                "inverted": false,
                "value": "SetAnimationName"
              },
              "parameters": [
                "SkinFat",
                "\"IdleFat\""
              ],
              "subInstructions": []
            }
          ],
          "events": []
        },
        {
          "disabled": false,
          "folded": false,
          "type": "BuiltinCommonInstructions::Comment",
          "color": {
            "b": 109,
            "g": 230,
            "r": 255,
            "textB": 0,
            "textG": 0,
            "textR": 0
          },
          "comment": "Variables",
          "comment2": ""
        },
        {
          "disabled": false,
          "folded": false,
          "type": "BuiltinCommonInstructions::Comment",
          "color": {
            "b": 109,
            "g": 230,
            "r": 255,
            "textB": 0,
            "textG": 0,
            "textR": 0
          },
          "comment": "FoodBar",
          "comment2": ""
        },
        {
          "disabled": false,
          "folded": false,
          "type": "BuiltinCommonInstructions::Standard",
          "conditions": [
            {
              "type": {
                "inverted": false,
                "value": "VarObjet"
              },
              "parameters": [
                "PlayerHitBox",
                "Gordura",
                "<=",
                "0"
              ],
              "subInstructions": []
            }
          ],
          "actions": [
            {
              "type": {
                "inverted": false,
                "value": "ModVarObjet"
              },
              "parameters": [
                "PlayerHitBox",
                "Gordura",
                "=",
                "1"
              ],
              "subInstructions": []
            }
          ],
          "events": []
        },
        {
          "disabled": false,
          "folded": false,
          "type": "BuiltinCommonInstructions::Standard",
          "conditions": [
            {
              "type": {
                "inverted": false,
                "value": "VarObjet"
              },
              "parameters": [
                "PlayerHitBox",
                "Gordura",
                "=",
                "1"
              ],
              "subInstructions": []
            }
          ],
          "actions": [
            {
              "type": {
                "inverted": false,
                "value": "SetAnimationName"
              },
              "parameters": [
                "FoodBar",
                "\"One\""
              ],
              "subInstructions": []
            }
          ],
          "events": []
        },
        {
          "disabled": false,
          "folded": false,
          "type": "BuiltinCommonInstructions::Standard",
          "conditions": [
            {
              "type": {
                "inverted": false,
                "value": "VarObjet"
              },
              "parameters": [
                "PlayerHitBox",
                "Gordura",
                "=",
                "2"
              ],
              "subInstructions": []
            }
          ],
          "actions": [
            {
              "type": {
                "inverted": false,
                "value": "SetAnimationName"
              },
              "parameters": [
                "FoodBar",
                "\"Two\""
              ],
              "subInstructions": []
            }
          ],
          "events": []
        },
        {
          "disabled": false,
          "folded": false,
          "type": "BuiltinCommonInstructions::Standard",
          "conditions": [
            {
              "type": {
                "inverted": false,
                "value": "VarObjet"
              },
              "parameters": [
                "PlayerHitBox",
                "Gordura",
                "=",
                "3"
              ],
              "subInstructions": []
            }
          ],
          "actions": [
            {
              "type": {
                "inverted": false,
                "value": "SetAnimationName"
              },
              "parameters": [
                "FoodBar",
                "\"Three\""
              ],
              "subInstructions": []
            }
          ],
          "events": []
        },
        {
          "disabled": false,
          "folded": false,
          "type": "BuiltinCommonInstructions::Standard",
          "conditions": [
            {
              "type": {
                "inverted": false,
                "value": "VarObjet"
              },
              "parameters": [
                "PlayerHitBox",
                "Gordura",
                "=",
                "4"
              ],
              "subInstructions": []
            }
          ],
          "actions": [
            {
              "type": {
                "inverted": false,
                "value": "SetAnimationName"
              },
              "parameters": [
                "FoodBar",
                "\"Four\""
              ],
              "subInstructions": []
            }
          ],
          "events": []
        },
        {
          "disabled": false,
          "folded": false,
          "type": "BuiltinCommonInstructions::Standard",
          "conditions": [
            {
              "type": {
                "inverted": false,
                "value": "VarObjet"
              },
              "parameters": [
                "PlayerHitBox",
                "Gordura",
                "=",
                "5\n"
              ],
              "subInstructions": []
            }
          ],
          "actions": [
            {
              "type": {
                "inverted": false,
                "value": "SetAnimationName"
              },
              "parameters": [
                "FoodBar",
                "\"Full\""
              ],
              "subInstructions": []
            }
          ],
          "events": []
        },
        {
          "disabled": false,
          "folded": false,
          "type": "BuiltinCommonInstructions::Standard",
          "conditions": [
            {
              "type": {
                "inverted": false,
                "value": "VarObjet"
              },
              "parameters": [
                "PlayerHitBox",
                "Gordura",
                ">=",
                "5"
              ],
              "subInstructions": []
            }
          ],
          "actions": [
            {
              "type": {
                "inverted": false,
                "value": "ModVarObjet"
              },
              "parameters": [
                "PlayerHitBox",
                "Gordura",
                "=",
                "5"
              ],
              "subInstructions": []
            }
          ],
          "events": []
        },
        {
          "disabled": false,
          "folded": false,
          "type": "BuiltinCommonInstructions::Comment",
          "color": {
            "b": 109,
            "g": 230,
            "r": 255,
            "textB": 0,
            "textG": 0,
            "textR": 0
          },
          "comment": "HideSkin",
          "comment2": ""
        },
        {
          "disabled": false,
          "folded": false,
          "type": "BuiltinCommonInstructions::Standard",
          "conditions": [
            {
              "type": {
                "inverted": false,
                "value": "VarObjet"
              },
              "parameters": [
                "PlayerHitBox",
                "Gordura",
                ">=",
                "3"
              ],
              "subInstructions": []
            }
          ],
          "actions": [
            {
              "type": {
                "inverted": false,
                "value": "Cache"
              },
              "parameters": [
                "SkinNormal"
              ],
              "subInstructions": []
            },
            {
              "type": {
                "inverted": false,
                "value": "Montre"
              },
              "parameters": [
                "SkinFat",
                ""
              ],
              "subInstructions": []
            },
            {
              "type": {
                "inverted": false,
                "value": "PlatformBehavior::MaxSpeed"
              },
              "parameters": [
                "PlayerHitBox",
                "PlatformerObject",
                "=",
                "100"
              ],
              "subInstructions": []
            }
          ],
          "events": []
        },
        {
          "disabled": false,
          "folded": false,
          "type": "BuiltinCommonInstructions::Standard",
          "conditions": [
            {
              "type": {
                "inverted": false,
                "value": "VarObjet"
              },
              "parameters": [
                "PlayerHitBox",
                "Gordura",
                "<",
                "3"
              ],
              "subInstructions": []
            }
          ],
          "actions": [
            {
              "type": {
                "inverted": false,
                "value": "Cache"
              },
              "parameters": [
                "SkinFat"
              ],
              "subInstructions": []
            },
            {
              "type": {
                "inverted": false,
                "value": "Montre"
              },
              "parameters": [
                "SkinNormal",
                ""
              ],
              "subInstructions": []
            }
          ],
          "events": []
        },
        {
          "disabled": false,
          "folded": false,
          "type": "BuiltinCommonInstructions::Comment",
          "color": {
            "b": 109,
            "g": 230,
            "r": 255,
            "textB": 0,
            "textG": 0,
            "textR": 0
          },
          "comment": "Eat",
          "comment2": ""
        },
        {
          "disabled": false,
          "folded": false,
          "type": "BuiltinCommonInstructions::Standard",
          "conditions": [
            {
              "type": {
                "inverted": false,
                "value": "CollisionNP"
              },
              "parameters": [
                "PlayerHitBox",
                "Fogao",
                "",
                "",
                ""
              ],
              "subInstructions": []
            },
            {
              "type": {
                "inverted": false,
                "value": "KeyPressed"
              },
              "parameters": [
                "",
                "Up"
              ],
              "subInstructions": []
            },
            {
              "type": {
                "inverted": false,
                "value": "Timer"
              },
              "parameters": [
                "",
                "2",
                "\"interaction\""
              ],
              "subInstructions": []
            }
          ],
          "actions": [
            {
              "type": {
                "inverted": false,
                "value": "ModVarObjet"
              },
              "parameters": [
                "PlayerHitBox",
                "Gordura",
                "+",
                "1"
              ],
              "subInstructions": []
            },
            {
              "type": {
                "inverted": false,
                "value": "ResetTimer"
              },
              "parameters": [
                "",
                "\"interaction\""
              ],
              "subInstructions": []
            }
          ],
          "events": []
        },
        {
          "disabled": false,
          "folded": false,
          "type": "BuiltinCommonInstructions::Standard",
          "conditions": [
            {
              "type": {
                "inverted": false,
                "value": "CollisionNP"
              },
              "parameters": [
                "PlayerHitBox",
                "Peso",
                "",
                "",
                ""
              ],
              "subInstructions": []
            },
            {
              "type": {
                "inverted": false,
                "value": "KeyPressed"
              },
              "parameters": [
                "",
                "Up"
              ],
              "subInstructions": []
            },
            {
              "type": {
                "inverted": false,
                "value": "Timer"
              },
              "parameters": [
                "",
                "2",
                "\"interaction\""
              ],
              "subInstructions": []
            }
          ],
          "actions": [
            {
              "type": {
                "inverted": false,
                "value": "ModVarObjet"
              },
              "parameters": [
                "PlayerHitBox",
                "Gordura",
                "-",
                "1"
              ],
              "subInstructions": []
            },
            {
              "type": {
                "inverted": false,
                "value": "ResetTimer"
              },
              "parameters": [
                "",
                "\"interaction\""
              ],
              "subInstructions": []
            }
          ],
          "events": []
        }
      ]
    }
  ],
  "eventsFunctionsExtensions": [],
  "externalLayouts": [],
  "externalSourceFiles": []
}